aiogram/contrib/__init__.py
aiogram/contrib/__meta__.py
aiogram/contrib/const.py
aiogram/contrib/py.typed
aiogram/contrib/middlewares/__init__.py
aiogram/contrib/middlewares/retry_request.py
aiogram/contrib/paginator/__init__.py
aiogram/contrib/paginator/callback_data.py
aiogram/contrib/paginator/factory.py
aiogram/contrib/paginator/paginator.py
aiogram/contrib/paginator/types.py
aiogram/contrib/paginator/utils.py
aiogram_contrib-1.1.2.dist-info/METADATA
aiogram_contrib-1.1.2.dist-info/WHEEL
aiogram_contrib-1.1.2.dist-info/licenses/LICENSE
aiogram_contrib-1.1.2.dist-info/RECORD
